{
  "schema_version": "urpg.dungeon3d_world.v1",
  "id": "dungeon3d.demo",
  "map_id": "ancient_crypt",
  "width": 5,
  "height": 5,
  "screen_width": 64,
  "screen_height": 48,
  "minimap_enabled": true,
  "auto_mapping": true,
  "mode": "3d",
  "camera": {
    "pos_x": 2.5,
    "pos_y": 2.5,
    "dir_x": 1.0,
    "dir_y": 0.0,
    "plane_x": 0.0,
    "plane_y": 0.66
  },
  "session": {
    "inventory": [],
    "discovered_cells": ["2,2"],
    "opened_doors": [],
    "revealed_secrets": [],
    "triggered_encounters": [],
    "completed_markers": [],
    "disabled_traps": [],
    "activated_switches": [],
    "alerted_patrols": [],
    "activated_puzzles": [],
    "patrol_indices": {},
    "current_hiding_spot": "",
    "current_floor_id": "crypt_b1",
    "event_log": []
  },
  "floors": [
    {
      "id": "crypt_b1",
      "display_name": "Ancient Crypt B1",
      "depth": 1,
      "ambient_sound": "ambience_crypt_low"
    },
    {
      "id": "crypt_b2",
      "display_name": "Ancient Crypt B2",
      "depth": 2,
      "ambient_sound": "ambience_crypt_deep"
    }
  ],
  "markers": [
    {
      "id": "obj_unlock_door",
      "label": "Unlock the lower stair door",
      "type": "objective",
      "x": 3,
      "y": 3,
      "floor_id": "crypt_b1",
      "visible": true,
      "completed": false
    },
    {
      "id": "marker_hidden_cache",
      "label": "Suspicious wall",
      "type": "secret",
      "x": 1,
      "y": 2,
      "floor_id": "crypt_b1",
      "visible": true,
      "completed": false
    },
    {
      "id": "marker_key",
      "label": "Crypt key",
      "type": "item",
      "x": 2,
      "y": 3,
      "floor_id": "crypt_b1",
      "visible": true,
      "completed": false
    }
  ],
  "notes": [
    {
      "id": "note_torch",
      "text": "The torch marks the safe path.",
      "x": 2,
      "y": 1,
      "floor_id": "crypt_b1"
    }
  ],
  "encounter_zones": [
    {
      "id": "zone_bone_pile",
      "encounter_tag": "crypt_bats",
      "x": 1,
      "y": 3,
      "radius": 0,
      "weight": 3,
      "floor_id": "crypt_b1",
      "repeatable": false
    }
  ],
  "lock_links": [
    {
      "id": "torch_switch_opens_door",
      "source_event_id": "torch_a",
      "target_door_id": "crypt_door",
      "required_item": "",
      "opens_on_interact": true
    }
  ],
  "traps": [
    {
      "id": "poison_plate",
      "x": 1,
      "y": 3,
      "floor_id": "crypt_b1",
      "effect_id": "poison",
      "damage": 12,
      "repeatable": false,
      "disarm_item": "trap_kit",
      "armed": true
    }
  ],
  "audio_zones": [
    {
      "id": "crypt_echo_chamber",
      "x": 2,
      "y": 2,
      "radius": 1,
      "floor_id": "crypt_b1",
      "ambient_sound": "ambience_crypt_echo",
      "reverb_preset": "stone_room"
    }
  ],
  "atmospheres": [
    {
      "id": "crypt_b1_haze",
      "floor_id": "crypt_b1",
      "weather": "dust_motes",
      "particle_preset": "slow_ash",
      "light_multiplier": 0.85
    },
    {
      "id": "crypt_b2_deep_fog",
      "floor_id": "crypt_b2",
      "weather": "deep_fog",
      "particle_preset": "cold_mist",
      "light_multiplier": 0.55
    }
  ],
  "patrol_routes": [
    {
      "id": "skeleton_guard_route",
      "enemy_id": "skeleton_guard",
      "floor_id": "crypt_b1",
      "waypoints": [
        {"x": 1, "y": 1},
        {"x": 2, "y": 1},
        {"x": 3, "y": 1}
      ],
      "vision_range": 2,
      "vision_width": 1,
      "active": true
    }
  ],
  "hiding_spots": [
    {
      "id": "shadow_urn",
      "x": 1,
      "y": 1,
      "floor_id": "crypt_b1",
      "required_item": ""
    }
  ],
  "puzzle_devices": [
    {
      "id": "pressure_plate_door",
      "type": "pressure_plate",
      "label": "Door Plate",
      "x": 3,
      "y": 2,
      "floor_id": "crypt_b1",
      "target_id": "crypt_door",
      "required_item": "",
      "active": true
    }
  ],
  "materials": [
    {
      "id": "stone",
      "wall_texture": "tiles/dungeon/stone_wall.png",
      "floor_texture": "tiles/dungeon/stone_floor.png",
      "ceiling_texture": "tiles/dungeon/stone_ceiling.png",
      "light": 1.0,
      "footstep_sound": "stone_step"
    },
    {
      "id": "dark",
      "wall_texture": "tiles/dungeon/dark_wall.png",
      "floor_texture": "tiles/dungeon/dark_floor.png",
      "ceiling_texture": "tiles/dungeon/dark_ceiling.png",
      "light": 0.45,
      "footstep_sound": "stone_echo"
    }
  ],
  "cells": [
    {"tile_id":"wall","material_id":"stone","event_id":"","door_id":"","required_item":"","encounter_tag":"","floor_transfer":"","blocking":true,"dark_zone":false,"stairs_up":false,"stairs_down":false,"secret":false,"locked":false},
    {"tile_id":"wall","material_id":"stone","event_id":"","door_id":"","required_item":"","encounter_tag":"","floor_transfer":"","blocking":true,"dark_zone":false,"stairs_up":false,"stairs_down":false,"secret":false,"locked":false},
    {"tile_id":"wall","material_id":"stone","event_id":"","door_id":"","required_item":"","encounter_tag":"","floor_transfer":"","blocking":true,"dark_zone":false,"stairs_up":false,"stairs_down":false,"secret":false,"locked":false},
    {"tile_id":"wall","material_id":"stone","event_id":"","door_id":"","required_item":"","encounter_tag":"","floor_transfer":"","blocking":true,"dark_zone":false,"stairs_up":false,"stairs_down":false,"secret":false,"locked":false},
    {"tile_id":"wall","material_id":"stone","event_id":"","door_id":"","required_item":"","encounter_tag":"","floor_transfer":"","blocking":true,"dark_zone":false,"stairs_up":false,"stairs_down":false,"secret":false,"locked":false},
    {"tile_id":"wall","material_id":"stone","event_id":"","door_id":"","required_item":"","encounter_tag":"","floor_transfer":"","blocking":true,"dark_zone":false,"stairs_up":false,"stairs_down":false,"secret":false,"locked":false},
    {"tile_id":"floor","material_id":"stone","event_id":"","door_id":"","required_item":"","encounter_tag":"","floor_transfer":"","blocking":false,"dark_zone":false,"stairs_up":false,"stairs_down":false,"secret":false,"locked":false},
    {"tile_id":"floor","material_id":"stone","event_id":"torch_a","door_id":"","required_item":"","encounter_tag":"","floor_transfer":"","blocking":false,"dark_zone":false,"stairs_up":false,"stairs_down":false,"secret":false,"locked":false},
    {"tile_id":"floor","material_id":"dark","event_id":"","door_id":"","required_item":"","encounter_tag":"","floor_transfer":"","blocking":false,"dark_zone":true,"stairs_up":false,"stairs_down":false,"secret":false,"locked":false},
    {"tile_id":"wall","material_id":"stone","event_id":"","door_id":"","required_item":"","encounter_tag":"","floor_transfer":"","blocking":true,"dark_zone":false,"stairs_up":false,"stairs_down":false,"secret":false,"locked":false},
    {"tile_id":"wall","material_id":"stone","event_id":"","door_id":"","required_item":"","encounter_tag":"","floor_transfer":"","blocking":true,"dark_zone":false,"stairs_up":false,"stairs_down":false,"secret":false,"locked":false},
    {"tile_id":"secret_wall","material_id":"stone","event_id":"hidden_cache","door_id":"","required_item":"","encounter_tag":"","floor_transfer":"","blocking":true,"dark_zone":false,"stairs_up":false,"stairs_down":false,"secret":true,"locked":false},
    {"tile_id":"floor","material_id":"stone","event_id":"spawn","door_id":"","required_item":"","encounter_tag":"","floor_transfer":"","blocking":false,"dark_zone":false,"stairs_up":true,"stairs_down":false,"secret":false,"locked":false},
    {"tile_id":"floor","material_id":"stone","event_id":"","door_id":"","required_item":"","encounter_tag":"crypt_slime","floor_transfer":"","blocking":false,"dark_zone":false,"stairs_up":false,"stairs_down":false,"secret":false,"locked":false},
    {"tile_id":"wall","material_id":"stone","event_id":"","door_id":"","required_item":"","encounter_tag":"","floor_transfer":"","blocking":true,"dark_zone":false,"stairs_up":false,"stairs_down":false,"secret":false,"locked":false},
    {"tile_id":"wall","material_id":"stone","event_id":"","door_id":"","required_item":"","encounter_tag":"","floor_transfer":"","blocking":true,"dark_zone":false,"stairs_up":false,"stairs_down":false,"secret":false,"locked":false},
    {"tile_id":"floor","material_id":"dark","event_id":"","door_id":"","required_item":"","encounter_tag":"","floor_transfer":"","blocking":false,"dark_zone":true,"stairs_up":false,"stairs_down":false,"secret":false,"locked":false},
    {"tile_id":"floor","material_id":"stone","event_id":"key_pickup","door_id":"","required_item":"","encounter_tag":"","floor_transfer":"","blocking":false,"dark_zone":false,"stairs_up":false,"stairs_down":false,"secret":false,"locked":false},
    {"tile_id":"locked_door","material_id":"stone","event_id":"door_a","door_id":"crypt_door","required_item":"crypt_key","encounter_tag":"","floor_transfer":"crypt_b2","blocking":true,"dark_zone":false,"stairs_up":false,"stairs_down":true,"secret":false,"locked":true},
    {"tile_id":"wall","material_id":"stone","event_id":"","door_id":"","required_item":"","encounter_tag":"","floor_transfer":"","blocking":true,"dark_zone":false,"stairs_up":false,"stairs_down":false,"secret":false,"locked":false},
    {"tile_id":"wall","material_id":"stone","event_id":"","door_id":"","required_item":"","encounter_tag":"","floor_transfer":"","blocking":true,"dark_zone":false,"stairs_up":false,"stairs_down":false,"secret":false,"locked":false},
    {"tile_id":"wall","material_id":"stone","event_id":"","door_id":"","required_item":"","encounter_tag":"","floor_transfer":"","blocking":true,"dark_zone":false,"stairs_up":false,"stairs_down":false,"secret":false,"locked":false},
    {"tile_id":"wall","material_id":"stone","event_id":"","door_id":"","required_item":"","encounter_tag":"","floor_transfer":"","blocking":true,"dark_zone":false,"stairs_up":false,"stairs_down":false,"secret":false,"locked":false},
    {"tile_id":"wall","material_id":"stone","event_id":"","door_id":"","required_item":"","encounter_tag":"","floor_transfer":"","blocking":true,"dark_zone":false,"stairs_up":false,"stairs_down":false,"secret":false,"locked":false},
    {"tile_id":"wall","material_id":"stone","event_id":"","door_id":"","required_item":"","encounter_tag":"","floor_transfer":"","blocking":true,"dark_zone":false,"stairs_up":false,"stairs_down":false,"secret":false,"locked":false}
  ]
}
