{
  "schema": "urpg/audio_to_ogg_manifest/v1",
  "generated_at": "2026-04-29T00:08:07+00:00",
  "repo_root": "C:\\dev\\URPG Maker",
  "roots": [
    "content",
    "data",
    "imports",
    "itch",
    "resources",
    "urpg stuff"
  ],
  "dry_run": false,
  "delete_source": false,
  "quality": 5,
  "summary": {
    "source_files": 0,
    "converted": 0,
    "existing_outputs": 0,
    "deleted_sources": 0,
    "skipped_lfs_pointers": 0,
    "failed": 0
  },
  "converted": [],
  "existing_outputs": [],
  "deleted_sources": [],
  "skipped_lfs_pointers": [],
  "failed": []
}
